prismformfactors/__init__.py
prismformfactors/average.py
prismformfactors/controls.py
prismformfactors/dataload.py
prismformfactors/formfactor.py
prismformfactors/functions.py
prismformfactors/polydispersity.py
prismformfactors/rotation.py
prismformfactors/visualize.py
prismformfactors/wuttke2d.py
prismformfactors-1.1.0.dist-info/METADATA
prismformfactors-1.1.0.dist-info/WHEEL
prismformfactors-1.1.0.dist-info/licenses/LICENSE
prismformfactors-1.1.0.dist-info/RECORD
