Metadata-Version: 2.4
Name: prismformfactors
Version: 1.1.0
Summary: Simulate 1-D and 2-D scattering form factors of prismatic objects
Project-URL: Repository, https://github.com/jules-marcone/prismformfactors
Project-URL: Issues, https://github.com/jules-marcone/prismformfactors/issues
Author-email: Marianne Impéror <marianne.imperor@universite-paris-saclay.fr>, Jules Marcone <jules.marcone@universite-paris-saclay.fr>
License:                     GNU GENERAL PUBLIC LICENSE
License-File: LICENSE
Keywords: Form factor,SANS,SAS,SAXS,Scattering,Small angle scattering
Classifier: Development Status :: 5 - Production/Stable
Classifier: Intended Audience :: Science/Research
Classifier: License :: OSI Approved :: GNU General Public License v3 (GPLv3)
Classifier: Programming Language :: Python :: 3.10
Classifier: Programming Language :: Python :: 3.11
Classifier: Programming Language :: Python :: 3.12
Classifier: Topic :: Scientific/Engineering :: Physics
Requires-Python: >=3.10
Requires-Dist: matplotlib
Requires-Dist: numpy
Requires-Dist: pylebedev
Requires-Dist: sasmodels
Requires-Dist: scipy
